{
    "$schema": "http://json-schema.org/draft-04/schema#",
    "type": "object",
    "description": "A set of SAML values that uniquely identify this person, consistently across TAS apps, and with any number of potential IdPs",
    "additionalProperties": false,
    "required": [
        "pt",
        "nameID",
        "entityID"
    ],
    "properties": {
        "pt": {
            "type": "string",
            "description": "principal type"
        },
        "nameID": {
            "type": "string"
        },
        "entityID": {
            "type": "string"
        }
    }
}